MANIFEST.in
README.md
VERSION
requirements.txt
setup.py
examples/repository.py
examples/foo/__init__.py
examples/foo/migrations/bc5a0a045a3d_.py
unimatrix/__init__.py
unimatrix.ext.rdbms.egg-info/PKG-INFO
unimatrix.ext.rdbms.egg-info/SOURCES.txt
unimatrix.ext.rdbms.egg-info/dependency_links.txt
unimatrix.ext.rdbms.egg-info/entry_points.txt
unimatrix.ext.rdbms.egg-info/requires.txt
unimatrix.ext.rdbms.egg-info/top_level.txt
unimatrix/ext/__init__.py
unimatrix/ext/rdbms/__init__.py
unimatrix/ext/rdbms/__pytest__.py
unimatrix/ext/rdbms/conftest.py
unimatrix/ext/rdbms/connection.py
unimatrix/ext/rdbms/connectionmanager.py
unimatrix/ext/rdbms/declarative.py
unimatrix/ext/rdbms/fixtures.py
unimatrix/ext/rdbms/package.json
unimatrix/ext/rdbms/queryrunner.py
unimatrix/ext/rdbms/repository.py
unimatrix/ext/rdbms/testsession.py
unimatrix/ext/rdbms/testsessionwrapper.py
unimatrix/ext/rdbms/migrations/__main__.py
unimatrix/ext/rdbms/migrations/env.py
unimatrix/ext/rdbms/migrations/script.py.mako
unimatrix/ext/rdbms/tests/__init__.py
unimatrix/ext/rdbms/tests/base.py
unimatrix/ext/rdbms/tests/conftest.py
unimatrix/ext/rdbms/tests/test_integration_sqlite.py
unimatrix/ext/rdbms/tests/test_integration_sqlite_maxconnections.py
unimatrix/ext/rdbms/tests/test_integration_testrollback.py
unimatrix/ext/rdbms/tests/test_integration_threading.py
unimatrix/ext/rdbms/tests/test_system_mysql.py
unimatrix/ext/rdbms/tests/test_system_postgresql.py
unimatrix/ext/rdbms/tests/test_system_testdatabases.py
unimatrix/ext/rdbms/tests/test_system_transaction_isolation.py
unimatrix/ext/rdbms/tests/test_unit_configure.py
unimatrix/ext/rdbms/tests/test_unit_repository.py